deepeda/__init__.py
deepeda/version.py
deepeda/object_detection/__init__.py
deepeda/object_detection/eda.py
deepeda/object_detection/utils.py
deepeda-0.1.0.dist-info/LICENSE
deepeda-0.1.0.dist-info/METADATA
deepeda-0.1.0.dist-info/WHEEL
deepeda-0.1.0.dist-info/top_level.txt
deepeda-0.1.0.dist-info/RECORD
